psy_ugrid-0.1.0.dist-info/entry_points.txt
psy_ugrid-0.1.0.dist-info/METADATA
psy_ugrid-0.1.0.dist-info/top_level.txt
psy_ugrid-0.1.0.dist-info/LGPL-3.0-only.txt
psy_ugrid-0.1.0.dist-info/CC0-1.0.txt
psy_ugrid-0.1.0.dist-info/RECORD
psy_ugrid-0.1.0.dist-info/WHEEL
psy_ugrid-0.1.0.dist-info/CC-BY-4.0.txt
psy_ugrid/decoder.py
psy_ugrid/__init__.py
psy_ugrid/_create_dual_node_mesh.c
psy_ugrid/_version.py
psy_ugrid/_create_dual_node_mesh.cpython-312-i386-linux-musl.so
psy_ugrid/_create_dual_node_mesh.pyx
psy_ugrid/ugrid.py
psy_ugrid/plotters.py
psy_ugrid/plugin.py
