Metadata-Version: 2.1
Name: psy-ugrid
Version: 0.1.0
Summary: A psyplot plugin for decoding unstructured grids following the UGRID conventions
Author-email: "Philipp S. Sommer" <philipp.sommer@hereon.de>
Maintainer-email: "Philipp S. Sommer" <philipp.sommer@hereon.de>
License: LGPL-3.0-only
Project-URL: Homepage, https://codebase.helmholtz.cloud/psyplot/psy-ugrid
Project-URL: Documentation, https://psyplot.github.io/psy-ugrid/
Project-URL: Source, https://codebase.helmholtz.cloud/psyplot/psy-ugrid
Project-URL: Tracker, https://codebase.helmholtz.cloud/psyplot/psy-ugrid/issues/
Keywords: visualization,psyplot,ugrid,unstructured,dual mesh,native,cython
Classifier: Development Status :: 5 - Production/Stable
Classifier: Topic :: Scientific/Engineering :: Visualization
Classifier: Topic :: Scientific/Engineering :: GIS
Classifier: Topic :: Scientific/Engineering
Classifier: Intended Audience :: Developers
Classifier: License :: OSI Approved :: European Union Public Licence 1.2 (EUPL 1.2)
Classifier: Operating System :: OS Independent
Classifier: Programming Language :: Python
Classifier: Programming Language :: Python :: 3
Classifier: Programming Language :: Python :: 3 :: Only
Classifier: Programming Language :: Python :: 3.9
Classifier: Programming Language :: Python :: 3.10
Classifier: Programming Language :: Python :: 3.11
Classifier: Programming Language :: Python :: 3.12
Classifier: Typing :: Typed
Requires-Python: >=3.9
License-File: LICENSES\CC-BY-4.0.txt
License-File: LICENSES\CC0-1.0.txt
License-File: LICENSES\LGPL-3.0-only.txt
Requires-Dist: psyplot
Requires-Dist: scipy
Provides-Extra: dev
Requires-Dist: psy-ugrid[testsite] ; extra == 'dev'
Requires-Dist: psy-ugrid[docs] ; extra == 'dev'
Requires-Dist: PyYAML ; extra == 'dev'
Requires-Dist: types-PyYAML ; extra == 'dev'
Requires-Dist: Cython ; extra == 'dev'
Provides-Extra: docs
Requires-Dist: autodocsumm ; extra == 'docs'
Requires-Dist: sphinx-rtd-theme ; extra == 'docs'
Requires-Dist: hereon-netcdf-sphinxext ; extra == 'docs'
Requires-Dist: sphinx-design ; extra == 'docs'
Requires-Dist: dask ; extra == 'docs'
Requires-Dist: netCDF4 ; extra == 'docs'
Requires-Dist: psy-simple >=1.5.0 ; extra == 'docs'
Requires-Dist: ipython ; extra == 'docs'
Requires-Dist: pickleshare ; extra == 'docs'
Provides-Extra: testsite
Requires-Dist: tox ; extra == 'testsite'
Requires-Dist: isort ==5.12.0 ; extra == 'testsite'
Requires-Dist: black ==23.1.0 ; extra == 'testsite'
Requires-Dist: blackdoc ==0.3.8 ; extra == 'testsite'
Requires-Dist: flake8 ==6.0.0 ; extra == 'testsite'
Requires-Dist: pre-commit ; extra == 'testsite'
Requires-Dist: mypy ; extra == 'testsite'
Requires-Dist: pytest-cov ; extra == 'testsite'
Requires-Dist: reuse ; extra == 'testsite'
Requires-Dist: cffconvert ; extra == 'testsite'
Requires-Dist: pytest-xdist ; extra == 'testsite'
